hich_restrict/__init__.py
hich_restrict/__main__.py
hich_restrict/contacts.py
hich_restrict/fragments.py
hich_restrict/restrict_manager.py
hich_restrict/timer.py
hich_restrict-0.1.6.dist-info/METADATA
hich_restrict-0.1.6.dist-info/WHEEL
hich_restrict-0.1.6.dist-info/entry_points.txt
hich_restrict-0.1.6.dist-info/RECORD
